inouts/__init__.py
inouts/example.py
inouts-0.0.2.dist-info/METADATA
inouts-0.0.2.dist-info/WHEEL
inouts-0.0.2.dist-info/licenses/LICENSE
inouts-0.0.2.dist-info/RECORD
